{"Group": "Metallic Dragon", "Space": "15 ft.", "Mythic": "0", "HP": 195, "Treasure": "triple", "FullText": "<link rel=\"stylesheet\"href=\"PF.css\"><div><h2>Metallic Dragon, Silver </h2><h3><i>The scales of this tall, elegant dragon shine like polished silver, and its tail has a feathered appearance.</i></h3><br></br></div><div class=\"heading\"><p class=\"alignleft\">Adult Silver Dragon</p><p class=\"alignright\">CR 14</p><div style=\"clear: both;\"></div></div><div><h5><b>XP </b>38,400</h5><h5>LG Huge dragon (cold)</h5><h5><b>Init </b>+4; <b>Senses </b>dragon senses, fog vision; Perception +25</h5><h5><b>Aura </b>frightful presence (180 ft., DC 23)</h5></div><hr/><div><h5><b>DEFENSE</b></h5></div><hr/><div><h5><b>AC </b>29, touch 8, flat-footed 29 (+21 natural, -2 size)</h5><h5><b>hp </b>195 (17d12+85)</h5><h5><b>Fort </b>+15, <b>Ref </b>+12, <b>Will </b>+17</h5><h5><b>DR </b>5/magic; <b>Immune </b>acid, cold, paralysis, sleep; <b>SR </b>25</h5><h5><b>Weaknesses </b>vulnerability to fire</h5></div><hr/><div><h5><b>OFFENSE</b></h5></div><hr/><div><h5><b>Spd </b>40 ft., fly 200 ft. (average); cloudwalking, graceful flight</h5><h5><b>Melee </b>bite +24 (2d8+12), 2 claws +23 (2d6+8), 2 wings +21 (1d8+4), tail slap +21 (2d6+12)</h5><h5><b>Space </b>15 ft.; <b>Reach </b>10 ft. (15 ft. with bite)</h5><h5><b>Special Attacks </b>breath weapon (50-ft. cone, DC 23, 12d8 cold), crush, paralyzing breath</h5><h5><b>Spell-Like Abilities</b> (CL 17th)</br>At will&mdash;<i>detect evil</i>,<i> feather fall</i>, <i>fog cloud</i></h5></h5><h5><b>Spells Known</b> (CL 7th)</br>3rd (5/day)&mdash;<i>dispel magic</i>,<i> wind wall</i></br>2nd (7/day)&mdash;<i>augury</i>,<i> cure moderate wounds</i>, <i>web</i> (DC 17)</br>1st (7/day)&mdash;<i>alarm</i>,<i> bless</i>,<i> divine favor</i>,<i> shield</i>,<i> true strike</i></br>0 (at will)&mdash;<i>detect magic</i>,<i> flare</i>,<i> light</i>,<i> message</i>,<i> prestidigitation</i>,<i> read magic</i>, <i>stabilize</i></h5></h5></div><hr/><div><h5><b>STATISTICS</b></h5></div><hr/><div><h5><b>Str</b> 27, <b>Dex</b> 10, <b>Con</b> 21, <b>Int</b> 20, <b>Wis</b> 21, <b>Cha</b> 20</h5><h5><b>Base Atk </b>+17; <b>CMB </b>+27; <b>CMD </b>37 (41 vs. trip)</h5><h5><b>Feats </b>Flyby Attack, Hover, Improved Initiative, Iron Will, Lighting Reflexes, Multiattack, Power Attack, Vital Strike, Weapon Focus (bite)</h5><h5><b>Skills </b>Acrobatics +17, Diplomacy +25, Fly +16, Heal +25, Intimidate +25, Knowledge (arcana, local, nobility) +25, Perception +25, Sense Motive +25, Spellcraft +25</h5><h5><b>Languages </b>Auran, Common, Draconic, Dwarven, Giant, Terran</h5><h5><b>SQ </b>change shape</h5></div><hr/><div><h5><b>ECOLOGY</b></h5></div><hr/><div><h5><b>Environment </b> temperate mountains</h5><h5><b>Organization </b>solitary</h5><h5><b>Treasure </b>triple</h5></div><hr/><div><h5><b>SPECIAL ABILITIES</b></h5></div><hr/><div><h5><b>Change Shape (Su)</b> A silver dragon can assume any animal or humanoid form three times per day as if using polymorph. </h5><h5><b>Cloudwalking (Su)</b> A very young or older silver dragon can tread on clouds or fog as though on solid ground. </h5><h5><b>Cold Aura (Su)</b> An old or older silver dragon is surrounded by an aura of cold. All creatures within 5 feet of the dragon take 1d6 points of cold damage at the beginning of the dragon's turn. An ancient dragon's aura extends to 10 feet. A great wyrm's aura damage increases to 2d6. A silver dragon can suppress or activate this aura at will as a free action.</h5><h5><b> Fog Vision (Ex)</b> A juvenile or older silver dragon can see perfectly well in fog and clouds.</h5><h5><b> Graceful Flight (Ex)</b> A young or older silver dragon's aerial maneuverability is one step better than normal. </h5><h5><b>Paralyzing Breath (Su)</b> Instead of a cone of cold, a silver dragon can breathe a cone of paralyzing gas. Creatures within the cone must succeed on a Fortitude save or be paralyzed for 1d6 rounds plus 1 round per age category of the dragon. </h5><h5><b>Reflective Scales (Su)</b> Any spell that targets an ancient or older silver dragon but fails to penetrate the silver dragon's spell resistance might be reflected. If the caster level check to penetrate the dragon's spell resistance is failed by 5 or more, the spell is reflected. If the check fails by 4 or less, the spell is merely wasted. This otherwise functions as spell turning.</h5><h5><b> Spell-Like Abilities (Sp)</b> A silver dragon gains the following spell-like abilities, usable at will upon reaching the listed age category. Very young-detect evil; Juvenile-feather fall; Adult-fog cloud; Old-control winds; Ancient-control weather; Great wyrm-reverse gravity.</h5><h5><b> True Courage (Ex)</b> A great wyrm silver dragon can fight on through pain and death. When reduced to below 0 hit points, it remains conscious, automatically stabilizes, and can continue to act (although it is staggered). If it takes damage or is the target of a spell that causes its death, it remains alive for 1 round and can act normally (it is not staggered for this final round). <table> <tr><th>Age Category</th><th>Special Abilities</th><th>Caster Level*</th></tr> <tr><td>Wyrmling</td><td>Change shape, cold subtype, immune to acid, paralyzing breath</td><td>-</td></tr> <tr><td>Very young</td><td>Cloudwalking, detect evil</td><td>-</td></tr> <tr><td>Young</td><td>Graceful flight</td><td>1st</td></tr> <tr><td>Juvenile</td><td>Fog vision, feather fall</td><td>3rd</td></tr> <tr><td>Young adult</td><td>DR 5/magic, spell resistance</td><td>5th</td></tr> <tr><td>Adult</td><td>Frightful presence, fog cloud</td><td>7th</td></tr> <tr><td>Mature adult</td><td>DR 10/magic</td><td>9th</td></tr> <tr><td>Old</td><td>Cold aura, control winds</td><td>11th</td></tr> <tr><td>Very old</td><td>DR 15/magic</td><td>13th</td></tr> <tr><td>Ancient</td><td>Reflective scales, control weather</td><td>15th</td></tr> <tr><td>Wyrm</td><td>DR 20/magic</td><td>17th</td></tr> <tr><td>Great wyrm</td><td>True courage, reverse gravity</td><td>19th</td></tr> <tr><td>* A silver dragon can cast cleric spells as arcane spells.</td></tr> </table> </h5></div><br></br><div><h4><p>Of all the dragons, silvers are the most courageous, holding themselves to a chivalrous code to help the weak, defeat evil, and behave in an honorable manner.</p></h4></div>", "Languages": "Auran, Common, Draconic, Dwarven, Giant, Terran", "Source": "PFRPG Bestiary", "Land": "1", "Organization": "solitary", "Ref": "12", "Climb": "0", "HD": "(17d12+85)", "AbilitiyScores": "Str 27, Dex 10, Con 21, Int 20, Wis 21, Cha 20", "Gear": "", "Ranged": "", "Type": "dragon", "Reach": "10 ft. (15 ft. with bite)", "DontUseRacialHD": "0", "id": 141, "SubType": "(cold)", "MonsterSource": "", "Feats": "Flyby Attack, Hover, Improved Initiative, Iron Will, Lighting Reflexes, Multiattack, Power Attack, Vital Strike, Weapon Focus (bite)", "AlternateNameForm": "", "CompanionFlag": "0", "MT": "0", "Class": "", "Fort": "15", "Fly": "1", "RacialMods": "", "AC": "29, touch 8, flat-footed 29", "Swim": "0", "Name": "Adult Silver Dragon", "VariantParent": "", "Skills": "Acrobatics +17, Diplomacy +25, Fly +16, Heal +25, Intimidate +25, Knowledge (arcana, local, nobility) +25, Perception +25, Sense Motive +25, Spellcraft +25", "ClassArchetypes": "", "IsTemplate": "0", "Will": "17", "Race": "", "CR": "14", "XP": 38400, "TemplatesApplied": "", "Environment": "temperate mountains", "CharacterFlag": "0", "OtherGear": "", "UniqueMonster": "0", "SQ": "change shape", "Saves": "Fort +15, Ref +12, Will +17", "Melee": "bite +24 (2d8+12), 2 claws +23 (2d6+8), 2 wings +21 (1d8+4), tail slap +21 (2d6+12)", "Burrow": "0", "CompanionFamiliarLink": "NULL", "AgeCategory": "adult", "MR": 0, "Speed": "40 ft., fly 200 ft. (average)", "Alignment": "LG", "Size": "Huge"}