{"Group": "", "Space": "15 ft.", "Mythic": "0", "HP": 114, "Treasure": "none", "FullText": "<link rel=\"stylesheet\"href=\"PF.css\"><div><h2>Star Monarch</h2><h3><i>This brilliantly colored moth rises taller than a house. A long tail resembling peacock feathers trails behind the creature.</i></h3><br></div><div class=\"heading\"><p class=\"alignleft\">Star Monarch</p><p class=\"alignright\">CR 9</p><div style=\"clear: both;\"></div></div><div><h5><b>XP </b>6,400</h5><h5>CG Huge magical beast </h5><h5><b>Init </b>+10; <b>Senses </b>darkvision 60 ft., low-light vision; Perception +16</h5><h5><b>Aura </b>dreamwarden (30 ft.)</h5></div><hr/><div><h5><b>DEFENSE</b></h5></div><hr/><div><h5><b>AC </b>22, touch 15, flat-footed 15 (+6 Dex, +1 dodge, +7 natural, -2 size)</h5><h5><b>hp </b>114 (12d10+48)</h5><h5><b>Fort </b>+12, <b>Ref </b>+14, <b>Will </b>+9</h5><h5><b>DR </b>5/silver; <b>Immune </b>cold; <b>SR </b>20</h5></div><hr/><div><h5><b>OFFENSE</b></h5></div><hr/><div><h5><b>Spd </b>30 ft., fly 80 ft. (average); starflight</h5><h5><b>Melee </b>2 claws +14 (1d8+4 plus grab), tail +14 (2d6+4 nonlethal)</h5><h5><b>Space </b>15 ft.; <b>Reach </b>5 ft. (15 ft. with tail)</h5><h5><b>Special Attacks </b>glowsap, rake (4 claws +10, 1d6+3)</h5><h5><b>Spell-Like Abilities</b> (CL 12th; concentration +16) </br>Constant&mdash;<i>entropic shield</i> </br>At Will&mdash;<i>dancing lights</i>, <i>restful</i> sleepAPG </br>3/day&mdash;<i>deep slumber</i> (DC 17), <i>dream</i>, <i>wandering star</i> motesAPG (DC 18) </br>1/day&mdash;<i>cloak of</i> <i>dream</i>sAPG (DC 20)</h5></h5></div><hr/><div><h5><b>STATISTICS</b></h5></div><hr/><div><h5><b>Str </b>18, <b>Dex </b>23, <b>Con </b>18, <b>Int </b> 11, <b>Wis </b>17, <b>Cha </b>18</h5><h5><b>Base Atk </b>+12; <b>CMB </b>+18 (+22 grapple); <b>CMD </b>35 (43 vs. trip)</h5><h5><b>Feats </b>Alertness, Dodge, Flyby Attack, Hover, Improved Initiative, Iron Will</h5><h5><b>Skills </b>Fly +14, Perception +16, Sense Motive +12</h5><h5><b>Languages </b>Common (can't speak); telepathy touch</h5><h5><b>SQ </b>navigational awareness, no breath, toxic flesh</h5></div><hr/><div><h5><b>ECOLOGY</b></h5></div><hr/><div><h5><b>Environment </b> any (Varisia)</h5><h5><b>Organization </b>solitary, pair, or rabble (3-6)</h5><h5><b>Treasure </b>none</h5></div><hr/><div><h5><b>SPECIAL ABILITIES</b></h5></div><hr/><div></h5><h5><b>Dreamwarden (Su)</b> Any sleeping creature within 30 feet of a star monarch is protected by <i>protection from evil</i> and <i>sanctuary</i> (Will DC 15 negates). The save DC is Constitution-based. </h5><h5><b>Glowsap (Ex)</b> As a standard action, a star monarch can spray a target within 30 feet with an adhesive spittle as a ranged touch attack. A creature struck is affected as a tanglefoot bag (Reflex DC 20 partial; see <i>Core Rulebook</i> 160). In addition, this adhesive glows under starlight or moonlight, limning the target as <i>faerie fire</i> if used outdoors at night. The save DC is Constitution-based. </h5><h5><b>Navigational Awareness (Ex)</b> Star monarchs never become lost and are immune to <i>maze</i> spells or any effect that would cause them to lose their sense of direction. </h5><h5><b>Starflight (Su)</b> A star monarch can survive in the void of outer space. It flies through space at an incredible speed. Although exact travel times vary, a trip within a single solar system should take 3d20 hours, while a trip beyond should take 3d20 days (or more, at the GM's discretion). </h5><h5><b>Toxic Flesh (Ex)</b> A star monarch's flesh is poisonous. A creature biting it or ingesting any part of its body becomes sickened for 1d4 rounds (Fortitude DC 20 negates) and is affected as if it had consumed a dose of arsenic (<i>Core Rulebook</i> 558).</h5></div><br><div><h4><p><p>Star monarchs are magical emissaries of Desna, the guide and protector of those who wander and guardian of <i>dream</i>s. They fly in glowing clouds through the void of space, visiting Golarion to watch over the faithful of Desna. Star monarchs spin streamers of sticky silver, weaving evanescent gossamer cocoons to enrobe those who slumber under their protection. These cocoons sublimate into wisps of half-remembered <i>dream</i>s with the coming of dawn. Star monarchs rarely intervene directly in combat, more often helping good creatures by aiding them from the shadows, guiding their paths, or guarding them while they sleep. Star monarchs can be found across Golarion in a variety of iridescent hues, and all are sacred to followers of the Song of the Spheres.</p></h4></div>", "Languages": "Common (can't speak); telepathy touch", "Source": "Inner Sea Bestiary", "Land": "1", "Organization": "solitary, pair, or rabble (3-6)", "Ref": "14", "Climb": "0", "HD": "(12d10+48)", "AbilitiyScores": "Str 18, Dex 23, Con 18, Int 11, Wis 17, Cha 18", "Gear": "", "Ranged": "", "Type": "magical beast", "Reach": "5 ft. (15 ft. with tail)", "DontUseRacialHD": "0", "id": 3585, "SubType": "", "MonsterSource": "", "Feats": "Alertness, Dodge, Flyby Attack, Hover, Improved Initiative, Iron Will", "AlternateNameForm": "", "CompanionFlag": "0", "MT": "0", "Class": "", "Fort": "12", "Fly": "1", "RacialMods": "", "AC": "22, touch 15, flat-footed 15", "Swim": "0", "Name": "Star Monarch", "VariantParent": "", "Skills": "Fly +14, Perception +16, Sense Motive +12", "ClassArchetypes": "", "IsTemplate": "0", "Will": "9", "Race": "", "CR": "9", "XP": 6400, "TemplatesApplied": "", "Environment": "any (Varisia)", "CharacterFlag": "0", "OtherGear": "", "UniqueMonster": "0", "SQ": "navigational awareness, no breath, toxic flesh", "Saves": "Fort +12, Ref +14, Will +9", "Melee": "2 claws +14 (1d8+4 plus grab), tail +14 (2d6+4 nonlethal)", "Burrow": "0", "CompanionFamiliarLink": "NULL", "AgeCategory": "NULL", "MR": 0, "Speed": "30 ft., fly 80 ft. (average)", "Alignment": "CG", "Size": "Huge"}