{"Group": "Beetle", "Space": "10 ft.", "Mythic": "0", "HP": 45, "Treasure": "none", "FullText": "<link rel=\"stylesheet\"href=\"PF.css\"><div><h2>Beetle, Giant Stag </h2><h3><i>With a sleek body and huge mandibles raised in a threatening pose, this large beetle stands firm in defense of its territory.</i></h3><br></br></div><div class=\"heading\"><p class=\"alignleft\">Giant Stag Beetle</p><p class=\"alignright\">CR 4</p><div style=\"clear: both;\"></div></div><div><h5><b>XP </b>1,200</h5><h5>N Large vermin </h5><h5><b>Init </b>+0; <b>Senses </b>darkvision 60 ft.; Perception +0</h5></div><hr/><div><h5><b>DEFENSE</b></h5></div><hr/><div><h5><b>AC </b>17, touch 9, flat-footed 17 (+8 natural, -1 size)</h5><h5><b>hp </b>45 (7d8+14)</h5><h5><b>Fort </b>+7, <b>Ref </b>+2, <b>Will </b>+2</h5><h5><b>Immune </b>mind-affecting effects</h5></div><hr/><div><h5><b>OFFENSE</b></h5></div><hr/><div><h5><b>Spd </b>20 ft., fly 20 ft. (poor)</h5><h5><b>Melee </b>bite +8 (2d8+6)</h5><h5><b>Space </b>10 ft.; <b>Reach </b>5 ft.</h5><h5><b>Special Attacks </b>trample (1d6+6, DC 17)</h5></div><hr/><div><h5><b>STATISTICS</b></h5></div><hr/><div><h5><b>Str</b> 19, <b>Dex</b> 10, <b>Con</b> 15, <b>Int</b> -, <b>Wis</b> 10, <b>Cha</b> 9</h5><h5><b>Base Atk </b>+5; <b>CMB </b>+10; <b>CMD </b>20 (28 vs. trip)</h5><h5><b>Skills </b>Fly -6</h5></div><hr/><div><h5><b>ECOLOGY</b></h5></div><hr/><div><h5><b>Environment </b> temperate forests</h5><h5><b>Organization </b>solitary, pair, or cluster (3-6)</h5><h5><b>Treasure </b>none</h5></div><br></br><div><h4><p>Nearly 10 feet long, giant stag beetles become serious dangers when they wander into logging camps due to their appetite for decaying wood. Called stag beetles because of their large, antler-like mandibles, they use these appendages to wrestle competing suitors and quickly put down enemy threats.</p><p>Variant species of these giant beetles exist as well. The two detailed below are the ones most commonly encountered.</p><p><b>Bombardier Beetle (CR 2):</b> This giant stag beetle has only 2 Hit Dice and is Medium sized, but can spray acid once per round in a 10-foot cone. Those in the cone must make a DC 11 Fortitude save or take 1d4+2 points of acid damage. The save DC is Constitution-based.</p><p><b>Goliath Beetle (CR 8):</b> The immense goliath beetle is a Huge stag beetle with 12 HD and the trample special ability.</p></h4></div>", "Languages": "", "Source": "PFRPG Bestiary", "Land": "1", "Organization": "solitary, pair, or cluster (3-6)", "Ref": "2", "Climb": "0", "HD": "(7d8+14)", "AbilitiyScores": "Str 19, Dex 10, Con 15, Int -, Wis 10, Cha 9", "Gear": "", "Ranged": "", "Type": "vermin", "Reach": "5 ft.", "DontUseRacialHD": "0", "id": 47, "SubType": "", "MonsterSource": "", "Feats": "", "AlternateNameForm": "", "CompanionFlag": "0", "MT": "0", "Class": "", "Fort": "7", "Fly": "1", "RacialMods": "", "AC": "17, touch 9, flat-footed 17", "Swim": "0", "Name": "Giant Stag Beetle", "VariantParent": "", "Skills": "Fly -6", "ClassArchetypes": "", "IsTemplate": "0", "Will": "2", "Race": "", "CR": "4", "XP": 1200, "TemplatesApplied": "", "Environment": "temperate forests", "CharacterFlag": "0", "OtherGear": "", "UniqueMonster": "0", "SQ": "", "Saves": "Fort +7, Ref +2, Will +2", "Melee": "bite +8 (2d8+6)", "Burrow": "0", "CompanionFamiliarLink": "NULL", "AgeCategory": "adult", "MR": 0, "Speed": "20 ft., fly 20 ft. (poor)", "Alignment": "N", "Size": "Large"}