{"Group": "Golem", "Space": "5 ft.", "Mythic": "0", "HP": 42, "Treasure": "none", "FullText": "<link rel=\"stylesheet\"href=\"PF.css\"><div><h2>Golem, Junk</h2><h3><i>A walking rubbish heap, this roughly man-shaped creature seems to be barely holding itself together.</i></h3><br></div><div class=\"heading\"><p class=\"alignleft\">Junk Golem</p><p class=\"alignright\">CR 4</p><div style=\"clear: both;\"></div></div><div><h5><b>XP </b>1,200</h5><h5>N Medium construct </h5><h5><b>Init </b>-1; <b>Senses </b>darkvision 60 ft., low-light vision; Perception +0</h5></div><hr/><div><h5><b>DEFENSE</b></h5></div><hr/><div><h5><b>AC </b>19, touch 9, flat-footed 19 (-1 Dex, +10 natural)</h5><h5><b>hp </b>42 (4d10+20); junk repair</h5><h5><b>Fort </b>+1, <b>Ref </b>+0, <b>Will </b>+1</h5><h5><b>DR </b>5/adamantine; <b>Immune </b>construct traits, magic</h5></div><hr/><div><h5><b>OFFENSE</b></h5></div><hr/><div><h5><b>Spd </b>30 ft.</h5><h5><b>Melee </b>2 slam +8 (1d6+4 plus disease)</h5><h5><b>Space </b>5 ft.; <b>Reach </b>5 ft.</h5><h5><b>Special Attacks </b>disease</h5></div><hr/><div><h5><b>STATISTICS</b></h5></div><hr/><div><h5><b>Str </b>18, <b>Dex </b>9, <b>Con </b>-, <b>Int </b> -, <b>Wis </b>11, <b>Cha </b>1</h5><h5><b>Base Atk </b>+4; <b>CMB </b>+8; <b>CMD </b>17</h5><h5><b>SQ </b>discorporate</h5></div><hr/><div><h5><b>ECOLOGY</b></h5></div><hr/><div><h5><b>Environment </b> any</h5><h5><b>Organization </b>solitary or gang (2-6)</h5><h5><b>Treasure </b>none</h5></div><hr/><div><h5><b>SPECIAL ABILITIES</b></h5></div><hr/><div></h5><h5><b>Discorporate (Ex)</b> A junk golem can break apart into its constituent pieces as a standard action, becoming a swarming mass of Tiny parts. It gains the swarm subtype, its space changes to 10 feet, and its reach changes to 0. In this form, it gains a swarm attack that deals 1d6 points of damage and inflicts disease, but loses its slam attacks. It can revert back to its normal form as a full-round action. </h5><h5><b>Disease (Ex)</b> <i>Tetanus</i>: Slam-injury; save Fort DC 12; <i>onset</i> 1d6 days; frequency 1 day; effect 1d4 Dex damage. Each time someone takes Dexterity damage from tetanus, there's a 50% chance his jaw muscles stiffen, preventing speech and the use of spells with verbal components for 24 hours; cure 2 consecutive saves. The save DC is Constitution-based. </h5><h5><b>Immunity to Magic (Ex)</b> A junk golem is immune to any spell or spell-like ability that allows spell resistance. In addition, certain spells and effects function differently against a junk golem, as noted below. <ul><li> A <i>shatter</i> spell causes a junk golem to discorporate and dazes it for 1 round. <li> A <i>grease</i> spell affects the junk golem as if it were <i>haste</i> for 1d6 rounds and ends any <i>slow</i> effect on it. <li> An <i>arcane lock</i> or <i>hold portal</i> spell affects the junk golem as if it were a <i>slow</i> spell for 1d6 rounds and breaks any <i>haste</i> effect on it. <li> A <i>wood shape</i> or <i>rusting grasp</i> spell deals 2d6 points of damage to a junk golem. </h5><h5><b>Junk Repair (Su)</b> A junk golem has fast healing 2 when in an area with a high concentration of debris, such as a refuse heap or the area created by another junk golem's discorporate ability.</ul></h5></div><br><div><h4><p><p>Junk golems are assembled from trash and spare parts, and often leave trails of garbage in their wakes. </h5><h5><b>CONSTRUCTION </b> A junk golem's body is made up of 250 pounds of assorted rubbish with 200 gp of spare metal and copper wire. JUNK GOLEM </h5><h5><b>CL </b>7th; </h5><h5><b>Price </b>10,200 gp </h5><h5><b>CONSTRUCTION </b>Requirements Craft Construct, <i>false life</i>, <i>lesser geas</i>, <i>minor creation</i>, <i>rusting grasp</i>, creator must be caster level 7th; </h5><h5><b>Skill </b>Craft (sculpture); </h5><h5><b>Cost </b>5,200 gp</p></h4></div>", "Languages": "", "Source": "PFRPG Bestiary 4", "Land": "1", "Organization": "solitary or gang (2-6)", "Ref": "0", "Climb": "0", "HD": "(4d10+20)", "AbilitiyScores": "Str 18, Dex 9, Con -, Int -, Wis 11, Cha 1", "Gear": "", "Ranged": "", "Type": "construct", "Reach": "5 ft.", "DontUseRacialHD": "0", "id": 5247, "SubType": "", "MonsterSource": "", "Feats": "", "AlternateNameForm": "", "CompanionFlag": "0", "MT": "0", "Class": "", "Fort": "1", "Fly": "0", "RacialMods": "", "AC": "19, touch 9, flat-footed 19", "Swim": "0", "Name": "Junk Golem", "VariantParent": "NULL", "Skills": "", "ClassArchetypes": "", "IsTemplate": "0", "Will": "1", "Race": "", "CR": "4", "XP": 1200, "TemplatesApplied": "", "Environment": "any", "CharacterFlag": "0", "OtherGear": "", "UniqueMonster": "0", "SQ": "discorporate", "Saves": "Fort +1, Ref +0, Will +1", "Melee": "2 slam +8 (1d6+4 plus disease)", "Burrow": "0", "CompanionFamiliarLink": "NULL", "AgeCategory": "NULL", "MR": 0, "Speed": "30 ft.", "Alignment": "N", "Size": "Medium"}